{
"companyName": "DefaultCompany",
"productName": "Programming Puzzle Game",
"dataUrl": "programming-puzzle-game.data.unityweb",
"asmCodeUrl": "programming-puzzle-game.asm.code.unityweb",
"asmMemoryUrl": "programming-puzzle-game.asm.memory.unityweb",
"asmFrameworkUrl": "programming-puzzle-game.asm.framework.unityweb",
"TOTAL_MEMORY": 268435456,
"graphicsAPI": ["WebGL 2.0", "WebGL 1.0"],
"webglContextAttributes": {"preserveDrawingBuffer": false},
"splashScreenStyle": "Dark",
"backgroundColor": "#231F20"
}